
[ 
	{
		"slug": "capitalismul-pe-muchie-de-cutit",
		"title": "Capitalismul pe muchie de cutit",
		"imgSrc": ""
		"subtitle": "https://www.libris.ro/ebook-capitalismul-pe-muchie-de-cutit-albena-FDE978-973-0-37299-1--p28378049.html",
		"year": 2022,
		"publisher": {
			"name": "Institutul Roman pentru Drepturile Omului",
			"url": "https://www.libris.ro/ebook-capitalismul-pe-muchie-de-cutit-albena-FDE978-973-0-37299-1--p28378049.html"
		},
		"description": "Lucrarea este axata pe teoria politica si prezinta o analiza a etapelor si tipologiilor sistemului capitalist, esecul de a articula o critica radicala a derapajelor sale, precum si cai posibile de depasire a acestuia. "
		
	}
]
